_11l.py
l11l-2021.5.1.dist-info/LICENSE.txt
l11l-2021.5.1.dist-info/METADATA
l11l-2021.5.1.dist-info/WHEEL
l11l-2021.5.1.dist-info/top_level.txt
l11l-2021.5.1.dist-info/RECORD
