Metadata-Version: 2.1
Name: l11l
Version: 2021.5.1
Summary: Python-11l compatibility layer
Home-page: UNKNOWN
Author: Alexander Tretyak
Author-email: alextretyak@users.noreply.github.com
License: MIT
Platform: UNKNOWN
Classifier: Operating System :: OS Independent
Classifier: Programming Language :: Python :: 3
Classifier: License :: OSI Approved :: MIT License
